marshal_web/__init__.py
marshal_web/app.py
marshal_web/main.py
marshal_web-0.1.1.dist-info/METADATA
marshal_web-0.1.1.dist-info/WHEEL
marshal_web-0.1.1.dist-info/entry_points.txt
marshal_web-0.1.1.dist-info/RECORD
