Metadata-Version: 2.1
Name: marshal-web
Version: 0.1.1
Summary: 
Author: Marshal Wu
Author-email: marshal.wu@qq.com
Requires-Python: >=3.10,<4.0
Classifier: Programming Language :: Python :: 3
Classifier: Programming Language :: Python :: 3.10
Classifier: Programming Language :: Python :: 3.11
Classifier: Programming Language :: Python :: 3.12
Requires-Dist: streamlit (>=1.38.0,<2.0.0)
